.coveragerc
.hgignore
.hgtags
CHANGES.rst
MANIFEST.in
README.rst
bootstrap.py
buildout.cfg
pytest.ini
setup.py
src/gocept/__init__.py
src/gocept.amqparchive.egg-info/PKG-INFO
src/gocept.amqparchive.egg-info/SOURCES.txt
src/gocept.amqparchive.egg-info/dependency_links.txt
src/gocept.amqparchive.egg-info/entry_points.txt
src/gocept.amqparchive.egg-info/namespace_packages.txt
src/gocept.amqparchive.egg-info/not-zip-safe
src/gocept.amqparchive.egg-info/requires.txt
src/gocept.amqparchive.egg-info/top_level.txt
src/gocept/amqparchive/__init__.py
src/gocept/amqparchive/archive.py
src/gocept/amqparchive/configure.zcml
src/gocept/amqparchive/connection.py
src/gocept/amqparchive/interfaces.py
src/gocept/amqparchive/reindex.py
src/gocept/amqparchive/testing.py
src/gocept/amqparchive/xml.py
src/gocept/amqparchive/browser/__init__.py
src/gocept/amqparchive/browser/index.html
src/gocept/amqparchive/browser/css/jquery-ui-1.8.14.ui-lightness.css
src/gocept/amqparchive/browser/css/style.css
src/gocept/amqparchive/browser/css/images/ui-bg_diagonals-thick_18_b81900_40x40.png
src/gocept/amqparchive/browser/css/images/ui-bg_diagonals-thick_20_666666_40x40.png
src/gocept/amqparchive/browser/css/images/ui-bg_flat_10_000000_40x100.png
src/gocept/amqparchive/browser/css/images/ui-bg_glass_100_f6f6f6_1x400.png
src/gocept/amqparchive/browser/css/images/ui-bg_glass_100_fdf5ce_1x400.png
src/gocept/amqparchive/browser/css/images/ui-bg_glass_65_ffffff_1x400.png
src/gocept/amqparchive/browser/css/images/ui-bg_gloss-wave_35_f6a828_500x100.png
src/gocept/amqparchive/browser/css/images/ui-bg_highlight-soft_100_eeeeee_1x100.png
src/gocept/amqparchive/browser/css/images/ui-bg_highlight-soft_75_ffe45c_1x100.png
src/gocept/amqparchive/browser/css/images/ui-icons_222222_256x240.png
src/gocept/amqparchive/browser/css/images/ui-icons_228ef1_256x240.png
src/gocept/amqparchive/browser/css/images/ui-icons_ef8c08_256x240.png
src/gocept/amqparchive/browser/css/images/ui-icons_ffd27a_256x240.png
src/gocept/amqparchive/browser/css/images/ui-icons_ffffff_256x240.png
src/gocept/amqparchive/browser/js/error.js
src/gocept/amqparchive/browser/js/search.js
src/gocept/amqparchive/browser/js/template.js
src/gocept/amqparchive/browser/js/lib/README.txt
src/gocept/amqparchive/browser/js/lib/elasticsearch-jquery.js
src/gocept/amqparchive/browser/js/lib/elasticsearch.js
