Metadata-Version: 2.1
Name: gocept.amqparchive
Version: 1.3.0.post1
Summary: Archiving, indexing and search for AMQP messages.
Home-page: https://bitbucket.org/gocept/gocept.amqparchive
Author: Wolfgang Schnerring, Christopher Grebs
Author-email: mail@gocept.com
License: ZPL
Platform: UNKNOWN
Provides-Extra: test
